{
    "@context": "http://iiif.io/api/presentation/2/context.json",
    "@id": "https://digirati-co-uk.github.io/nlw-rcamw/park_the_newtown_hall.json",
    "@type": "sc:Manifest",
    "label": "park_the_newtown_hall",
    "metadata": [
        {
            "label": "Title",
            "value": "park_the_newtown_hall"
        }
    ],
    "sequences": [
        {
            "@id": "https://digirati-co-uk.github.io/nlw-rcamw/park_the_newtown_hall.json/sequence/0",
            "@type": "sc:Sequence",
            "canvases": [
                {
                    "@id": "https://digirati-co-uk.github.io/nlw-rcamw/park_the_newtown_hall.json/sequence/0/canvas/1",
                    "@type": "sc:Canvas",
                    "height": 2550,
                    "images": [
                        {
                            "@id": "https://dlc.services/iiif-img/10/1/park_the_newtown_hall_DP03713.tif/anno",
                            "@type": "oa:Annotation",
                            "motivation": "sc:painting",
                            "on": "https://digirati-co-uk.github.io/nlw-rcamw/park_the_newtown_hall.json/sequence/0/canvas/1",
                            "resource": {
                                "@id": "https://dlc.services/iiif-img/10/1/park_the_newtown_hall_DP03713.tif/full/!2000,2000/0/default.jpg",
                                "@type": "dctypes:Image",
                                "height": 2550,
                                "service": {
                                    "@id": "https://dlc.services/iiif-img/10/1/park_the_newtown_hall_DP03713.tif",
                                    "height": 2550,
                                    "profile": "http://iiif.io/api/image/2/level1.json",
                                    "protocol": "http://iiif.io/api/image",
                                    "width": 3509
                                },
                                "width": 3509
                            }
                        }
                    ],
                    "label": "DP03713.tif",
                    "thumbnail": {
                        "@id": "https://dlc.services/thumbs/10/1/park_the_newtown_hall_DP03713.tif/full/full/0/default.jpg",
                        "@type": "dctypes:Image",
                        "service": {
                            "@context": "http://iiif.io/api/image/2/context.json",
                            "@id": "https://dlc.services/thumbs/10/1/park_the_newtown_hall_DP03713.tif",
                            "height": 744,
                            "profile": [
                                "http://iiif.io/api/image/2/level0.json",
                                {
                                    "formats": [
                                        "jpg"
                                    ],
                                    "qualities": [
                                        "color"
                                    ],
                                    "supports": [
                                        "sizeByWhListed"
                                    ]
                                }
                            ],
                            "sizes": [
                                {
                                    "height": 744,
                                    "width": 1024
                                },
                                {
                                    "height": 291,
                                    "width": 400
                                },
                                {
                                    "height": 145,
                                    "width": 200
                                },
                                {
                                    "height": 73,
                                    "width": 100
                                }
                            ],
                            "width": 1024
                        }
                    },
                    "width": 3509
                },
                {
                    "@id": "https://digirati-co-uk.github.io/nlw-rcamw/park_the_newtown_hall.json/sequence/0/canvas/2",
                    "@type": "sc:Canvas",
                    "height": 2550,
                    "images": [
                        {
                            "@id": "https://dlc.services/iiif-img/10/1/park_the_newtown_hall_DP03714.tif/anno",
                            "@type": "oa:Annotation",
                            "motivation": "sc:painting",
                            "on": "https://digirati-co-uk.github.io/nlw-rcamw/park_the_newtown_hall.json/sequence/0/canvas/2",
                            "resource": {
                                "@id": "https://dlc.services/iiif-img/10/1/park_the_newtown_hall_DP03714.tif/full/!2000,2000/0/default.jpg",
                                "@type": "dctypes:Image",
                                "height": 2550,
                                "service": {
                                    "@id": "https://dlc.services/iiif-img/10/1/park_the_newtown_hall_DP03714.tif",
                                    "height": 2550,
                                    "profile": "http://iiif.io/api/image/2/level1.json",
                                    "protocol": "http://iiif.io/api/image",
                                    "width": 3509
                                },
                                "width": 3509
                            }
                        }
                    ],
                    "label": "DP03714.tif",
                    "thumbnail": {
                        "@id": "https://dlc.services/thumbs/10/1/park_the_newtown_hall_DP03714.tif/full/full/0/default.jpg",
                        "@type": "dctypes:Image",
                        "service": {
                            "@context": "http://iiif.io/api/image/2/context.json",
                            "@id": "https://dlc.services/thumbs/10/1/park_the_newtown_hall_DP03714.tif",
                            "height": 744,
                            "profile": [
                                "http://iiif.io/api/image/2/level0.json",
                                {
                                    "formats": [
                                        "jpg"
                                    ],
                                    "qualities": [
                                        "color"
                                    ],
                                    "supports": [
                                        "sizeByWhListed"
                                    ]
                                }
                            ],
                            "sizes": [
                                {
                                    "height": 744,
                                    "width": 1024
                                },
                                {
                                    "height": 291,
                                    "width": 400
                                },
                                {
                                    "height": 145,
                                    "width": 200
                                },
                                {
                                    "height": 73,
                                    "width": 100
                                }
                            ],
                            "width": 1024
                        }
                    },
                    "width": 3509
                },
                {
                    "@id": "https://digirati-co-uk.github.io/nlw-rcamw/park_the_newtown_hall.json/sequence/0/canvas/3",
                    "@type": "sc:Canvas",
                    "height": 2550,
                    "images": [
                        {
                            "@id": "https://dlc.services/iiif-img/10/1/park_the_newtown_hall_DP03715.tif/anno",
                            "@type": "oa:Annotation",
                            "motivation": "sc:painting",
                            "on": "https://digirati-co-uk.github.io/nlw-rcamw/park_the_newtown_hall.json/sequence/0/canvas/3",
                            "resource": {
                                "@id": "https://dlc.services/iiif-img/10/1/park_the_newtown_hall_DP03715.tif/full/!2000,2000/0/default.jpg",
                                "@type": "dctypes:Image",
                                "height": 2550,
                                "service": {
                                    "@id": "https://dlc.services/iiif-img/10/1/park_the_newtown_hall_DP03715.tif",
                                    "height": 2550,
                                    "profile": "http://iiif.io/api/image/2/level1.json",
                                    "protocol": "http://iiif.io/api/image",
                                    "width": 3509
                                },
                                "width": 3509
                            }
                        }
                    ],
                    "label": "DP03715.tif",
                    "thumbnail": {
                        "@id": "https://dlc.services/thumbs/10/1/park_the_newtown_hall_DP03715.tif/full/full/0/default.jpg",
                        "@type": "dctypes:Image",
                        "service": {
                            "@context": "http://iiif.io/api/image/2/context.json",
                            "@id": "https://dlc.services/thumbs/10/1/park_the_newtown_hall_DP03715.tif",
                            "height": 744,
                            "profile": [
                                "http://iiif.io/api/image/2/level0.json",
                                {
                                    "formats": [
                                        "jpg"
                                    ],
                                    "qualities": [
                                        "color"
                                    ],
                                    "supports": [
                                        "sizeByWhListed"
                                    ]
                                }
                            ],
                            "sizes": [
                                {
                                    "height": 744,
                                    "width": 1024
                                },
                                {
                                    "height": 291,
                                    "width": 400
                                },
                                {
                                    "height": 145,
                                    "width": 200
                                },
                                {
                                    "height": 73,
                                    "width": 100
                                }
                            ],
                            "width": 1024
                        }
                    },
                    "width": 3509
                },
                {
                    "@id": "https://digirati-co-uk.github.io/nlw-rcamw/park_the_newtown_hall.json/sequence/0/canvas/4",
                    "@type": "sc:Canvas",
                    "height": 2550,
                    "images": [
                        {
                            "@id": "https://dlc.services/iiif-img/10/1/park_the_newtown_hall_DP03716.tif/anno",
                            "@type": "oa:Annotation",
                            "motivation": "sc:painting",
                            "on": "https://digirati-co-uk.github.io/nlw-rcamw/park_the_newtown_hall.json/sequence/0/canvas/4",
                            "resource": {
                                "@id": "https://dlc.services/iiif-img/10/1/park_the_newtown_hall_DP03716.tif/full/!2000,2000/0/default.jpg",
                                "@type": "dctypes:Image",
                                "height": 2550,
                                "service": {
                                    "@id": "https://dlc.services/iiif-img/10/1/park_the_newtown_hall_DP03716.tif",
                                    "height": 2550,
                                    "profile": "http://iiif.io/api/image/2/level1.json",
                                    "protocol": "http://iiif.io/api/image",
                                    "width": 3509
                                },
                                "width": 3509
                            }
                        }
                    ],
                    "label": "DP03716.tif",
                    "thumbnail": {
                        "@id": "https://dlc.services/thumbs/10/1/park_the_newtown_hall_DP03716.tif/full/full/0/default.jpg",
                        "@type": "dctypes:Image",
                        "service": {
                            "@context": "http://iiif.io/api/image/2/context.json",
                            "@id": "https://dlc.services/thumbs/10/1/park_the_newtown_hall_DP03716.tif",
                            "height": 744,
                            "profile": [
                                "http://iiif.io/api/image/2/level0.json",
                                {
                                    "formats": [
                                        "jpg"
                                    ],
                                    "qualities": [
                                        "color"
                                    ],
                                    "supports": [
                                        "sizeByWhListed"
                                    ]
                                }
                            ],
                            "sizes": [
                                {
                                    "height": 744,
                                    "width": 1024
                                },
                                {
                                    "height": 291,
                                    "width": 400
                                },
                                {
                                    "height": 145,
                                    "width": 200
                                },
                                {
                                    "height": 73,
                                    "width": 100
                                }
                            ],
                            "width": 1024
                        }
                    },
                    "width": 3509
                },
                {
                    "@id": "https://digirati-co-uk.github.io/nlw-rcamw/park_the_newtown_hall.json/sequence/0/canvas/5",
                    "@type": "sc:Canvas",
                    "height": 3509,
                    "images": [
                        {
                            "@id": "https://dlc.services/iiif-img/10/1/park_the_newtown_hall_DP03717.tif/anno",
                            "@type": "oa:Annotation",
                            "motivation": "sc:painting",
                            "on": "https://digirati-co-uk.github.io/nlw-rcamw/park_the_newtown_hall.json/sequence/0/canvas/5",
                            "resource": {
                                "@id": "https://dlc.services/iiif-img/10/1/park_the_newtown_hall_DP03717.tif/full/!2000,2000/0/default.jpg",
                                "@type": "dctypes:Image",
                                "height": 3509,
                                "service": {
                                    "@id": "https://dlc.services/iiif-img/10/1/park_the_newtown_hall_DP03717.tif",
                                    "height": 3509,
                                    "profile": "http://iiif.io/api/image/2/level1.json",
                                    "protocol": "http://iiif.io/api/image",
                                    "width": 2550
                                },
                                "width": 2550
                            }
                        }
                    ],
                    "label": "DP03717.tif",
                    "thumbnail": {
                        "@id": "https://dlc.services/thumbs/10/1/park_the_newtown_hall_DP03717.tif/full/full/0/default.jpg",
                        "@type": "dctypes:Image",
                        "service": {
                            "@context": "http://iiif.io/api/image/2/context.json",
                            "@id": "https://dlc.services/thumbs/10/1/park_the_newtown_hall_DP03717.tif",
                            "height": 1024,
                            "profile": [
                                "http://iiif.io/api/image/2/level0.json",
                                {
                                    "formats": [
                                        "jpg"
                                    ],
                                    "qualities": [
                                        "color"
                                    ],
                                    "supports": [
                                        "sizeByWhListed"
                                    ]
                                }
                            ],
                            "sizes": [
                                {
                                    "height": 1024,
                                    "width": 744
                                },
                                {
                                    "height": 400,
                                    "width": 291
                                },
                                {
                                    "height": 200,
                                    "width": 145
                                },
                                {
                                    "height": 100,
                                    "width": 73
                                }
                            ],
                            "width": 744
                        }
                    },
                    "width": 2550
                },
                {
                    "@id": "https://digirati-co-uk.github.io/nlw-rcamw/park_the_newtown_hall.json/sequence/0/canvas/6",
                    "@type": "sc:Canvas",
                    "height": 2550,
                    "images": [
                        {
                            "@id": "https://dlc.services/iiif-img/10/1/park_the_newtown_hall_DP03718.tif/anno",
                            "@type": "oa:Annotation",
                            "motivation": "sc:painting",
                            "on": "https://digirati-co-uk.github.io/nlw-rcamw/park_the_newtown_hall.json/sequence/0/canvas/6",
                            "resource": {
                                "@id": "https://dlc.services/iiif-img/10/1/park_the_newtown_hall_DP03718.tif/full/!2000,2000/0/default.jpg",
                                "@type": "dctypes:Image",
                                "height": 2550,
                                "service": {
                                    "@id": "https://dlc.services/iiif-img/10/1/park_the_newtown_hall_DP03718.tif",
                                    "height": 2550,
                                    "profile": "http://iiif.io/api/image/2/level1.json",
                                    "protocol": "http://iiif.io/api/image",
                                    "width": 3509
                                },
                                "width": 3509
                            }
                        }
                    ],
                    "label": "DP03718.tif",
                    "thumbnail": {
                        "@id": "https://dlc.services/thumbs/10/1/park_the_newtown_hall_DP03718.tif/full/full/0/default.jpg",
                        "@type": "dctypes:Image",
                        "service": {
                            "@context": "http://iiif.io/api/image/2/context.json",
                            "@id": "https://dlc.services/thumbs/10/1/park_the_newtown_hall_DP03718.tif",
                            "height": 744,
                            "profile": [
                                "http://iiif.io/api/image/2/level0.json",
                                {
                                    "formats": [
                                        "jpg"
                                    ],
                                    "qualities": [
                                        "color"
                                    ],
                                    "supports": [
                                        "sizeByWhListed"
                                    ]
                                }
                            ],
                            "sizes": [
                                {
                                    "height": 744,
                                    "width": 1024
                                },
                                {
                                    "height": 291,
                                    "width": 400
                                },
                                {
                                    "height": 145,
                                    "width": 200
                                },
                                {
                                    "height": 73,
                                    "width": 100
                                }
                            ],
                            "width": 1024
                        }
                    },
                    "width": 3509
                },
                {
                    "@id": "https://digirati-co-uk.github.io/nlw-rcamw/park_the_newtown_hall.json/sequence/0/canvas/7",
                    "@type": "sc:Canvas",
                    "height": 2550,
                    "images": [
                        {
                            "@id": "https://dlc.services/iiif-img/10/1/park_the_newtown_hall_DP03719.tif/anno",
                            "@type": "oa:Annotation",
                            "motivation": "sc:painting",
                            "on": "https://digirati-co-uk.github.io/nlw-rcamw/park_the_newtown_hall.json/sequence/0/canvas/7",
                            "resource": {
                                "@id": "https://dlc.services/iiif-img/10/1/park_the_newtown_hall_DP03719.tif/full/!2000,2000/0/default.jpg",
                                "@type": "dctypes:Image",
                                "height": 2550,
                                "service": {
                                    "@id": "https://dlc.services/iiif-img/10/1/park_the_newtown_hall_DP03719.tif",
                                    "height": 2550,
                                    "profile": "http://iiif.io/api/image/2/level1.json",
                                    "protocol": "http://iiif.io/api/image",
                                    "width": 3509
                                },
                                "width": 3509
                            }
                        }
                    ],
                    "label": "DP03719.tif",
                    "thumbnail": {
                        "@id": "https://dlc.services/thumbs/10/1/park_the_newtown_hall_DP03719.tif/full/full/0/default.jpg",
                        "@type": "dctypes:Image",
                        "service": {
                            "@context": "http://iiif.io/api/image/2/context.json",
                            "@id": "https://dlc.services/thumbs/10/1/park_the_newtown_hall_DP03719.tif",
                            "height": 744,
                            "profile": [
                                "http://iiif.io/api/image/2/level0.json",
                                {
                                    "formats": [
                                        "jpg"
                                    ],
                                    "qualities": [
                                        "color"
                                    ],
                                    "supports": [
                                        "sizeByWhListed"
                                    ]
                                }
                            ],
                            "sizes": [
                                {
                                    "height": 744,
                                    "width": 1024
                                },
                                {
                                    "height": 291,
                                    "width": 400
                                },
                                {
                                    "height": 145,
                                    "width": 200
                                },
                                {
                                    "height": 73,
                                    "width": 100
                                }
                            ],
                            "width": 1024
                        }
                    },
                    "width": 3509
                },
                {
                    "@id": "https://digirati-co-uk.github.io/nlw-rcamw/park_the_newtown_hall.json/sequence/0/canvas/8",
                    "@type": "sc:Canvas",
                    "height": 2550,
                    "images": [
                        {
                            "@id": "https://dlc.services/iiif-img/10/1/park_the_newtown_hall_DP03720.tif/anno",
                            "@type": "oa:Annotation",
                            "motivation": "sc:painting",
                            "on": "https://digirati-co-uk.github.io/nlw-rcamw/park_the_newtown_hall.json/sequence/0/canvas/8",
                            "resource": {
                                "@id": "https://dlc.services/iiif-img/10/1/park_the_newtown_hall_DP03720.tif/full/!2000,2000/0/default.jpg",
                                "@type": "dctypes:Image",
                                "height": 2550,
                                "service": {
                                    "@id": "https://dlc.services/iiif-img/10/1/park_the_newtown_hall_DP03720.tif",
                                    "height": 2550,
                                    "profile": "http://iiif.io/api/image/2/level1.json",
                                    "protocol": "http://iiif.io/api/image",
                                    "width": 3509
                                },
                                "width": 3509
                            }
                        }
                    ],
                    "label": "DP03720.tif",
                    "thumbnail": {
                        "@id": "https://dlc.services/thumbs/10/1/park_the_newtown_hall_DP03720.tif/full/full/0/default.jpg",
                        "@type": "dctypes:Image",
                        "service": {
                            "@context": "http://iiif.io/api/image/2/context.json",
                            "@id": "https://dlc.services/thumbs/10/1/park_the_newtown_hall_DP03720.tif",
                            "height": 744,
                            "profile": [
                                "http://iiif.io/api/image/2/level0.json",
                                {
                                    "formats": [
                                        "jpg"
                                    ],
                                    "qualities": [
                                        "color"
                                    ],
                                    "supports": [
                                        "sizeByWhListed"
                                    ]
                                }
                            ],
                            "sizes": [
                                {
                                    "height": 744,
                                    "width": 1024
                                },
                                {
                                    "height": 291,
                                    "width": 400
                                },
                                {
                                    "height": 145,
                                    "width": 200
                                },
                                {
                                    "height": 73,
                                    "width": 100
                                }
                            ],
                            "width": 1024
                        }
                    },
                    "width": 3509
                },
                {
                    "@id": "https://digirati-co-uk.github.io/nlw-rcamw/park_the_newtown_hall.json/sequence/0/canvas/9",
                    "@type": "sc:Canvas",
                    "height": 2550,
                    "images": [
                        {
                            "@id": "https://dlc.services/iiif-img/10/1/park_the_newtown_hall_DP03721.tif/anno",
                            "@type": "oa:Annotation",
                            "motivation": "sc:painting",
                            "on": "https://digirati-co-uk.github.io/nlw-rcamw/park_the_newtown_hall.json/sequence/0/canvas/9",
                            "resource": {
                                "@id": "https://dlc.services/iiif-img/10/1/park_the_newtown_hall_DP03721.tif/full/!2000,2000/0/default.jpg",
                                "@type": "dctypes:Image",
                                "height": 2550,
                                "service": {
                                    "@id": "https://dlc.services/iiif-img/10/1/park_the_newtown_hall_DP03721.tif",
                                    "height": 2550,
                                    "profile": "http://iiif.io/api/image/2/level1.json",
                                    "protocol": "http://iiif.io/api/image",
                                    "width": 3509
                                },
                                "width": 3509
                            }
                        }
                    ],
                    "label": "DP03721.tif",
                    "thumbnail": {
                        "@id": "https://dlc.services/thumbs/10/1/park_the_newtown_hall_DP03721.tif/full/full/0/default.jpg",
                        "@type": "dctypes:Image",
                        "service": {
                            "@context": "http://iiif.io/api/image/2/context.json",
                            "@id": "https://dlc.services/thumbs/10/1/park_the_newtown_hall_DP03721.tif",
                            "height": 744,
                            "profile": [
                                "http://iiif.io/api/image/2/level0.json",
                                {
                                    "formats": [
                                        "jpg"
                                    ],
                                    "qualities": [
                                        "color"
                                    ],
                                    "supports": [
                                        "sizeByWhListed"
                                    ]
                                }
                            ],
                            "sizes": [
                                {
                                    "height": 744,
                                    "width": 1024
                                },
                                {
                                    "height": 291,
                                    "width": 400
                                },
                                {
                                    "height": 145,
                                    "width": 200
                                },
                                {
                                    "height": 73,
                                    "width": 100
                                }
                            ],
                            "width": 1024
                        }
                    },
                    "width": 3509
                },
                {
                    "@id": "https://digirati-co-uk.github.io/nlw-rcamw/park_the_newtown_hall.json/sequence/0/canvas/10",
                    "@type": "sc:Canvas",
                    "height": 2550,
                    "images": [
                        {
                            "@id": "https://dlc.services/iiif-img/10/1/park_the_newtown_hall_DP03722.tif/anno",
                            "@type": "oa:Annotation",
                            "motivation": "sc:painting",
                            "on": "https://digirati-co-uk.github.io/nlw-rcamw/park_the_newtown_hall.json/sequence/0/canvas/10",
                            "resource": {
                                "@id": "https://dlc.services/iiif-img/10/1/park_the_newtown_hall_DP03722.tif/full/!2000,2000/0/default.jpg",
                                "@type": "dctypes:Image",
                                "height": 2550,
                                "service": {
                                    "@id": "https://dlc.services/iiif-img/10/1/park_the_newtown_hall_DP03722.tif",
                                    "height": 2550,
                                    "profile": "http://iiif.io/api/image/2/level1.json",
                                    "protocol": "http://iiif.io/api/image",
                                    "width": 3509
                                },
                                "width": 3509
                            }
                        }
                    ],
                    "label": "DP03722.tif",
                    "thumbnail": {
                        "@id": "https://dlc.services/thumbs/10/1/park_the_newtown_hall_DP03722.tif/full/full/0/default.jpg",
                        "@type": "dctypes:Image",
                        "service": {
                            "@context": "http://iiif.io/api/image/2/context.json",
                            "@id": "https://dlc.services/thumbs/10/1/park_the_newtown_hall_DP03722.tif",
                            "height": 744,
                            "profile": [
                                "http://iiif.io/api/image/2/level0.json",
                                {
                                    "formats": [
                                        "jpg"
                                    ],
                                    "qualities": [
                                        "color"
                                    ],
                                    "supports": [
                                        "sizeByWhListed"
                                    ]
                                }
                            ],
                            "sizes": [
                                {
                                    "height": 744,
                                    "width": 1024
                                },
                                {
                                    "height": 291,
                                    "width": 400
                                },
                                {
                                    "height": 145,
                                    "width": 200
                                },
                                {
                                    "height": 73,
                                    "width": 100
                                }
                            ],
                            "width": 1024
                        }
                    },
                    "width": 3509
                },
                {
                    "@id": "https://digirati-co-uk.github.io/nlw-rcamw/park_the_newtown_hall.json/sequence/0/canvas/11",
                    "@type": "sc:Canvas",
                    "height": 2550,
                    "images": [
                        {
                            "@id": "https://dlc.services/iiif-img/10/1/park_the_newtown_hall_DP03723.tif/anno",
                            "@type": "oa:Annotation",
                            "motivation": "sc:painting",
                            "on": "https://digirati-co-uk.github.io/nlw-rcamw/park_the_newtown_hall.json/sequence/0/canvas/11",
                            "resource": {
                                "@id": "https://dlc.services/iiif-img/10/1/park_the_newtown_hall_DP03723.tif/full/!2000,2000/0/default.jpg",
                                "@type": "dctypes:Image",
                                "height": 2550,
                                "service": {
                                    "@id": "https://dlc.services/iiif-img/10/1/park_the_newtown_hall_DP03723.tif",
                                    "height": 2550,
                                    "profile": "http://iiif.io/api/image/2/level1.json",
                                    "protocol": "http://iiif.io/api/image",
                                    "width": 3509
                                },
                                "width": 3509
                            }
                        }
                    ],
                    "label": "DP03723.tif",
                    "thumbnail": {
                        "@id": "https://dlc.services/thumbs/10/1/park_the_newtown_hall_DP03723.tif/full/full/0/default.jpg",
                        "@type": "dctypes:Image",
                        "service": {
                            "@context": "http://iiif.io/api/image/2/context.json",
                            "@id": "https://dlc.services/thumbs/10/1/park_the_newtown_hall_DP03723.tif",
                            "height": 744,
                            "profile": [
                                "http://iiif.io/api/image/2/level0.json",
                                {
                                    "formats": [
                                        "jpg"
                                    ],
                                    "qualities": [
                                        "color"
                                    ],
                                    "supports": [
                                        "sizeByWhListed"
                                    ]
                                }
                            ],
                            "sizes": [
                                {
                                    "height": 744,
                                    "width": 1024
                                },
                                {
                                    "height": 291,
                                    "width": 400
                                },
                                {
                                    "height": 145,
                                    "width": 200
                                },
                                {
                                    "height": 73,
                                    "width": 100
                                }
                            ],
                            "width": 1024
                        }
                    },
                    "width": 3509
                },
                {
                    "@id": "https://digirati-co-uk.github.io/nlw-rcamw/park_the_newtown_hall.json/sequence/0/canvas/12",
                    "@type": "sc:Canvas",
                    "height": 2550,
                    "images": [
                        {
                            "@id": "https://dlc.services/iiif-img/10/1/park_the_newtown_hall_DP03724.tif/anno",
                            "@type": "oa:Annotation",
                            "motivation": "sc:painting",
                            "on": "https://digirati-co-uk.github.io/nlw-rcamw/park_the_newtown_hall.json/sequence/0/canvas/12",
                            "resource": {
                                "@id": "https://dlc.services/iiif-img/10/1/park_the_newtown_hall_DP03724.tif/full/!2000,2000/0/default.jpg",
                                "@type": "dctypes:Image",
                                "height": 2550,
                                "service": {
                                    "@id": "https://dlc.services/iiif-img/10/1/park_the_newtown_hall_DP03724.tif",
                                    "height": 2550,
                                    "profile": "http://iiif.io/api/image/2/level1.json",
                                    "protocol": "http://iiif.io/api/image",
                                    "width": 3509
                                },
                                "width": 3509
                            }
                        }
                    ],
                    "label": "DP03724.tif",
                    "thumbnail": {
                        "@id": "https://dlc.services/thumbs/10/1/park_the_newtown_hall_DP03724.tif/full/full/0/default.jpg",
                        "@type": "dctypes:Image",
                        "service": {
                            "@context": "http://iiif.io/api/image/2/context.json",
                            "@id": "https://dlc.services/thumbs/10/1/park_the_newtown_hall_DP03724.tif",
                            "height": 744,
                            "profile": [
                                "http://iiif.io/api/image/2/level0.json",
                                {
                                    "formats": [
                                        "jpg"
                                    ],
                                    "qualities": [
                                        "color"
                                    ],
                                    "supports": [
                                        "sizeByWhListed"
                                    ]
                                }
                            ],
                            "sizes": [
                                {
                                    "height": 744,
                                    "width": 1024
                                },
                                {
                                    "height": 291,
                                    "width": 400
                                },
                                {
                                    "height": 145,
                                    "width": 200
                                },
                                {
                                    "height": 73,
                                    "width": 100
                                }
                            ],
                            "width": 1024
                        }
                    },
                    "width": 3509
                },
                {
                    "@id": "https://digirati-co-uk.github.io/nlw-rcamw/park_the_newtown_hall.json/sequence/0/canvas/13",
                    "@type": "sc:Canvas",
                    "height": 2550,
                    "images": [
                        {
                            "@id": "https://dlc.services/iiif-img/10/1/park_the_newtown_hall_DP03725.tif/anno",
                            "@type": "oa:Annotation",
                            "motivation": "sc:painting",
                            "on": "https://digirati-co-uk.github.io/nlw-rcamw/park_the_newtown_hall.json/sequence/0/canvas/13",
                            "resource": {
                                "@id": "https://dlc.services/iiif-img/10/1/park_the_newtown_hall_DP03725.tif/full/!2000,2000/0/default.jpg",
                                "@type": "dctypes:Image",
                                "height": 2550,
                                "service": {
                                    "@id": "https://dlc.services/iiif-img/10/1/park_the_newtown_hall_DP03725.tif",
                                    "height": 2550,
                                    "profile": "http://iiif.io/api/image/2/level1.json",
                                    "protocol": "http://iiif.io/api/image",
                                    "width": 3509
                                },
                                "width": 3509
                            }
                        }
                    ],
                    "label": "DP03725.tif",
                    "thumbnail": {
                        "@id": "https://dlc.services/thumbs/10/1/park_the_newtown_hall_DP03725.tif/full/full/0/default.jpg",
                        "@type": "dctypes:Image",
                        "service": {
                            "@context": "http://iiif.io/api/image/2/context.json",
                            "@id": "https://dlc.services/thumbs/10/1/park_the_newtown_hall_DP03725.tif",
                            "height": 744,
                            "profile": [
                                "http://iiif.io/api/image/2/level0.json",
                                {
                                    "formats": [
                                        "jpg"
                                    ],
                                    "qualities": [
                                        "color"
                                    ],
                                    "supports": [
                                        "sizeByWhListed"
                                    ]
                                }
                            ],
                            "sizes": [
                                {
                                    "height": 744,
                                    "width": 1024
                                },
                                {
                                    "height": 291,
                                    "width": 400
                                },
                                {
                                    "height": 145,
                                    "width": 200
                                },
                                {
                                    "height": 73,
                                    "width": 100
                                }
                            ],
                            "width": 1024
                        }
                    },
                    "width": 3509
                },
                {
                    "@id": "https://digirati-co-uk.github.io/nlw-rcamw/park_the_newtown_hall.json/sequence/0/canvas/14",
                    "@type": "sc:Canvas",
                    "height": 2550,
                    "images": [
                        {
                            "@id": "https://dlc.services/iiif-img/10/1/park_the_newtown_hall_DP03726.tif/anno",
                            "@type": "oa:Annotation",
                            "motivation": "sc:painting",
                            "on": "https://digirati-co-uk.github.io/nlw-rcamw/park_the_newtown_hall.json/sequence/0/canvas/14",
                            "resource": {
                                "@id": "https://dlc.services/iiif-img/10/1/park_the_newtown_hall_DP03726.tif/full/!2000,2000/0/default.jpg",
                                "@type": "dctypes:Image",
                                "height": 2550,
                                "service": {
                                    "@id": "https://dlc.services/iiif-img/10/1/park_the_newtown_hall_DP03726.tif",
                                    "height": 2550,
                                    "profile": "http://iiif.io/api/image/2/level1.json",
                                    "protocol": "http://iiif.io/api/image",
                                    "width": 3509
                                },
                                "width": 3509
                            }
                        }
                    ],
                    "label": "DP03726.tif",
                    "thumbnail": {
                        "@id": "https://dlc.services/thumbs/10/1/park_the_newtown_hall_DP03726.tif/full/full/0/default.jpg",
                        "@type": "dctypes:Image",
                        "service": {
                            "@context": "http://iiif.io/api/image/2/context.json",
                            "@id": "https://dlc.services/thumbs/10/1/park_the_newtown_hall_DP03726.tif",
                            "height": 744,
                            "profile": [
                                "http://iiif.io/api/image/2/level0.json",
                                {
                                    "formats": [
                                        "jpg"
                                    ],
                                    "qualities": [
                                        "color"
                                    ],
                                    "supports": [
                                        "sizeByWhListed"
                                    ]
                                }
                            ],
                            "sizes": [
                                {
                                    "height": 744,
                                    "width": 1024
                                },
                                {
                                    "height": 291,
                                    "width": 400
                                },
                                {
                                    "height": 145,
                                    "width": 200
                                },
                                {
                                    "height": 73,
                                    "width": 100
                                }
                            ],
                            "width": 1024
                        }
                    },
                    "width": 3509
                },
                {
                    "@id": "https://digirati-co-uk.github.io/nlw-rcamw/park_the_newtown_hall.json/sequence/0/canvas/15",
                    "@type": "sc:Canvas",
                    "height": 2550,
                    "images": [
                        {
                            "@id": "https://dlc.services/iiif-img/10/1/park_the_newtown_hall_DP03727.tif/anno",
                            "@type": "oa:Annotation",
                            "motivation": "sc:painting",
                            "on": "https://digirati-co-uk.github.io/nlw-rcamw/park_the_newtown_hall.json/sequence/0/canvas/15",
                            "resource": {
                                "@id": "https://dlc.services/iiif-img/10/1/park_the_newtown_hall_DP03727.tif/full/!2000,2000/0/default.jpg",
                                "@type": "dctypes:Image",
                                "height": 2550,
                                "service": {
                                    "@id": "https://dlc.services/iiif-img/10/1/park_the_newtown_hall_DP03727.tif",
                                    "height": 2550,
                                    "profile": "http://iiif.io/api/image/2/level1.json",
                                    "protocol": "http://iiif.io/api/image",
                                    "width": 3509
                                },
                                "width": 3509
                            }
                        }
                    ],
                    "label": "DP03727.tif",
                    "thumbnail": {
                        "@id": "https://dlc.services/thumbs/10/1/park_the_newtown_hall_DP03727.tif/full/full/0/default.jpg",
                        "@type": "dctypes:Image",
                        "service": {
                            "@context": "http://iiif.io/api/image/2/context.json",
                            "@id": "https://dlc.services/thumbs/10/1/park_the_newtown_hall_DP03727.tif",
                            "height": 744,
                            "profile": [
                                "http://iiif.io/api/image/2/level0.json",
                                {
                                    "formats": [
                                        "jpg"
                                    ],
                                    "qualities": [
                                        "color"
                                    ],
                                    "supports": [
                                        "sizeByWhListed"
                                    ]
                                }
                            ],
                            "sizes": [
                                {
                                    "height": 744,
                                    "width": 1024
                                },
                                {
                                    "height": 291,
                                    "width": 400
                                },
                                {
                                    "height": 145,
                                    "width": 200
                                },
                                {
                                    "height": 73,
                                    "width": 100
                                }
                            ],
                            "width": 1024
                        }
                    },
                    "width": 3509
                },
                {
                    "@id": "https://digirati-co-uk.github.io/nlw-rcamw/park_the_newtown_hall.json/sequence/0/canvas/16",
                    "@type": "sc:Canvas",
                    "height": 2550,
                    "images": [
                        {
                            "@id": "https://dlc.services/iiif-img/10/1/park_the_newtown_hall_DP03728.tif/anno",
                            "@type": "oa:Annotation",
                            "motivation": "sc:painting",
                            "on": "https://digirati-co-uk.github.io/nlw-rcamw/park_the_newtown_hall.json/sequence/0/canvas/16",
                            "resource": {
                                "@id": "https://dlc.services/iiif-img/10/1/park_the_newtown_hall_DP03728.tif/full/!2000,2000/0/default.jpg",
                                "@type": "dctypes:Image",
                                "height": 2550,
                                "service": {
                                    "@id": "https://dlc.services/iiif-img/10/1/park_the_newtown_hall_DP03728.tif",
                                    "height": 2550,
                                    "profile": "http://iiif.io/api/image/2/level1.json",
                                    "protocol": "http://iiif.io/api/image",
                                    "width": 3509
                                },
                                "width": 3509
                            }
                        }
                    ],
                    "label": "DP03728.tif",
                    "thumbnail": {
                        "@id": "https://dlc.services/thumbs/10/1/park_the_newtown_hall_DP03728.tif/full/full/0/default.jpg",
                        "@type": "dctypes:Image",
                        "service": {
                            "@context": "http://iiif.io/api/image/2/context.json",
                            "@id": "https://dlc.services/thumbs/10/1/park_the_newtown_hall_DP03728.tif",
                            "height": 744,
                            "profile": [
                                "http://iiif.io/api/image/2/level0.json",
                                {
                                    "formats": [
                                        "jpg"
                                    ],
                                    "qualities": [
                                        "color"
                                    ],
                                    "supports": [
                                        "sizeByWhListed"
                                    ]
                                }
                            ],
                            "sizes": [
                                {
                                    "height": 744,
                                    "width": 1024
                                },
                                {
                                    "height": 291,
                                    "width": 400
                                },
                                {
                                    "height": 145,
                                    "width": 200
                                },
                                {
                                    "height": 73,
                                    "width": 100
                                }
                            ],
                            "width": 1024
                        }
                    },
                    "width": 3509
                }
            ],
            "label": "Sequence 0"
        }
    ]
}