{
  "@context": "http://iiif.io/api/presentation/2/context.json",
  "@id": "https://digirati-co-uk.github.io/nlw-rcamw/skinner_st.json",
  "@type": "sc:Manifest",
  "metadata": [
    {
      "label": "Title",
      "value": "Created by DLCS"
    }
  ],
  "sequences": [
    {
      "@id": "https://digirati-co-uk.github.io/nlw-rcamw/skinner_st.json/sequence/0",
      "@type": "sc:Sequence",
      "label": "Sequence 0",
      "canvases": [
        {
          "@id": "https://digirati-co-uk.github.io/nlw-rcamw/skinner_st.json/sequence/0/canvas/1",
          "@type": "sc:Canvas",
          "thumbnail": {
            "@id": "https://dlc.services/thumbs/10/1/skinner_st_DP04113.tif/full/full/0/default.jpg",
            "@type": "dctypes:Image",
            "service": {
              "@context": "http://iiif.io/api/image/2/context.json",
              "@id": "https://dlc.services/thumbs/10/1/skinner_st_DP04113.tif",
              "profile": [
                "http://iiif.io/api/image/2/level0.json",
                {
                  "formats": [
                    "jpg"
                  ],
                  "qualities": [
                    "color"
                  ],
                  "supports": [
                    "sizeByWhListed"
                  ]
                }
              ],
              "width": 1024,
              "height": 744,
              "sizes": [
                {
                  "width": 1024,
                  "height": 744
                },
                {
                  "width": 400,
                  "height": 291
                },
                {
                  "width": 200,
                  "height": 145
                },
                {
                  "width": 100,
                  "height": 73
                }
              ]
            }
          },
          "height": 2550,
          "width": 3509,
          "images": [
            {
              "@id": "https://dlc.services/iiif-img/10/1/skinner_st_DP04113.tif/anno",
              "@type": "oa:Annotation",
              "motivation": "sc:painting",
              "resource": {
                "@id": "https://dlc.services/iiif-img/10/1/skinner_st_DP04113.tif/full/!2000,2000/0/default.jpg",
                "@type": "dctypes:Image",
                "height": 2550,
                "width": 3509,
                "service": {
                  "@id": "https://dlc.services/iiif-img/10/1/skinner_st_DP04113.tif",
                  "protocol": "http://iiif.io/api/image",
                  "height": 2550,
                  "width": 3509,
                  "profile": "http://iiif.io/api/image/2/level1.json"
                }
              },
              "on": "https://digirati-co-uk.github.io/nlw-rcamw/skinner_st.json/sequence/0/canvas/1"
            }
          ]
        },
        {
          "@id": "https://digirati-co-uk.github.io/nlw-rcamw/skinner_st.json/sequence/0/canvas/2",
          "@type": "sc:Canvas",
          "thumbnail": {
            "@id": "https://dlc.services/thumbs/10/1/skinner_st_DP04114.tif/full/full/0/default.jpg",
            "@type": "dctypes:Image",
            "service": {
              "@context": "http://iiif.io/api/image/2/context.json",
              "@id": "https://dlc.services/thumbs/10/1/skinner_st_DP04114.tif",
              "profile": [
                "http://iiif.io/api/image/2/level0.json",
                {
                  "formats": [
                    "jpg"
                  ],
                  "qualities": [
                    "color"
                  ],
                  "supports": [
                    "sizeByWhListed"
                  ]
                }
              ],
              "width": 1024,
              "height": 744,
              "sizes": [
                {
                  "width": 1024,
                  "height": 744
                },
                {
                  "width": 400,
                  "height": 291
                },
                {
                  "width": 200,
                  "height": 145
                },
                {
                  "width": 100,
                  "height": 73
                }
              ]
            }
          },
          "height": 2550,
          "width": 3509,
          "images": [
            {
              "@id": "https://dlc.services/iiif-img/10/1/skinner_st_DP04114.tif/anno",
              "@type": "oa:Annotation",
              "motivation": "sc:painting",
              "resource": {
                "@id": "https://dlc.services/iiif-img/10/1/skinner_st_DP04114.tif/full/!2000,2000/0/default.jpg",
                "@type": "dctypes:Image",
                "height": 2550,
                "width": 3509,
                "service": {
                  "@id": "https://dlc.services/iiif-img/10/1/skinner_st_DP04114.tif",
                  "protocol": "http://iiif.io/api/image",
                  "height": 2550,
                  "width": 3509,
                  "profile": "http://iiif.io/api/image/2/level1.json"
                }
              },
              "on": "https://digirati-co-uk.github.io/nlw-rcamw/skinner_st.json/sequence/0/canvas/2"
            }
          ]
        },
        {
          "@id": "https://digirati-co-uk.github.io/nlw-rcamw/skinner_st.json/sequence/0/canvas/3",
          "@type": "sc:Canvas",
          "thumbnail": {
            "@id": "https://dlc.services/thumbs/10/1/skinner_st_DP04115.tif/full/full/0/default.jpg",
            "@type": "dctypes:Image",
            "service": {
              "@context": "http://iiif.io/api/image/2/context.json",
              "@id": "https://dlc.services/thumbs/10/1/skinner_st_DP04115.tif",
              "profile": [
                "http://iiif.io/api/image/2/level0.json",
                {
                  "formats": [
                    "jpg"
                  ],
                  "qualities": [
                    "color"
                  ],
                  "supports": [
                    "sizeByWhListed"
                  ]
                }
              ],
              "width": 1024,
              "height": 744,
              "sizes": [
                {
                  "width": 1024,
                  "height": 744
                },
                {
                  "width": 400,
                  "height": 291
                },
                {
                  "width": 200,
                  "height": 145
                },
                {
                  "width": 100,
                  "height": 73
                }
              ]
            }
          },
          "height": 2550,
          "width": 3509,
          "images": [
            {
              "@id": "https://dlc.services/iiif-img/10/1/skinner_st_DP04115.tif/anno",
              "@type": "oa:Annotation",
              "motivation": "sc:painting",
              "resource": {
                "@id": "https://dlc.services/iiif-img/10/1/skinner_st_DP04115.tif/full/!2000,2000/0/default.jpg",
                "@type": "dctypes:Image",
                "height": 2550,
                "width": 3509,
                "service": {
                  "@id": "https://dlc.services/iiif-img/10/1/skinner_st_DP04115.tif",
                  "protocol": "http://iiif.io/api/image",
                  "height": 2550,
                  "width": 3509,
                  "profile": "http://iiif.io/api/image/2/level1.json"
                }
              },
              "on": "https://digirati-co-uk.github.io/nlw-rcamw/skinner_st.json/sequence/0/canvas/3"
            }
          ]
        },
        {
          "@id": "https://digirati-co-uk.github.io/nlw-rcamw/skinner_st.json/sequence/0/canvas/4",
          "@type": "sc:Canvas",
          "thumbnail": {
            "@id": "https://dlc.services/thumbs/10/1/skinner_st_DP04116.tif/full/full/0/default.jpg",
            "@type": "dctypes:Image",
            "service": {
              "@context": "http://iiif.io/api/image/2/context.json",
              "@id": "https://dlc.services/thumbs/10/1/skinner_st_DP04116.tif",
              "profile": [
                "http://iiif.io/api/image/2/level0.json",
                {
                  "formats": [
                    "jpg"
                  ],
                  "qualities": [
                    "color"
                  ],
                  "supports": [
                    "sizeByWhListed"
                  ]
                }
              ],
              "width": 1024,
              "height": 744,
              "sizes": [
                {
                  "width": 1024,
                  "height": 744
                },
                {
                  "width": 400,
                  "height": 291
                },
                {
                  "width": 200,
                  "height": 145
                },
                {
                  "width": 100,
                  "height": 73
                }
              ]
            }
          },
          "height": 2550,
          "width": 3509,
          "images": [
            {
              "@id": "https://dlc.services/iiif-img/10/1/skinner_st_DP04116.tif/anno",
              "@type": "oa:Annotation",
              "motivation": "sc:painting",
              "resource": {
                "@id": "https://dlc.services/iiif-img/10/1/skinner_st_DP04116.tif/full/!2000,2000/0/default.jpg",
                "@type": "dctypes:Image",
                "height": 2550,
                "width": 3509,
                "service": {
                  "@id": "https://dlc.services/iiif-img/10/1/skinner_st_DP04116.tif",
                  "protocol": "http://iiif.io/api/image",
                  "height": 2550,
                  "width": 3509,
                  "profile": "http://iiif.io/api/image/2/level1.json"
                }
              },
              "on": "https://digirati-co-uk.github.io/nlw-rcamw/skinner_st.json/sequence/0/canvas/4"
            }
          ]
        },
        {
          "@id": "https://digirati-co-uk.github.io/nlw-rcamw/skinner_st.json/sequence/0/canvas/5",
          "@type": "sc:Canvas",
          "thumbnail": {
            "@id": "https://dlc.services/thumbs/10/1/skinner_st_DP04117.tif/full/full/0/default.jpg",
            "@type": "dctypes:Image",
            "service": {
              "@context": "http://iiif.io/api/image/2/context.json",
              "@id": "https://dlc.services/thumbs/10/1/skinner_st_DP04117.tif",
              "profile": [
                "http://iiif.io/api/image/2/level0.json",
                {
                  "formats": [
                    "jpg"
                  ],
                  "qualities": [
                    "color"
                  ],
                  "supports": [
                    "sizeByWhListed"
                  ]
                }
              ],
              "width": 1024,
              "height": 744,
              "sizes": [
                {
                  "width": 1024,
                  "height": 744
                },
                {
                  "width": 400,
                  "height": 291
                },
                {
                  "width": 200,
                  "height": 145
                },
                {
                  "width": 100,
                  "height": 73
                }
              ]
            }
          },
          "height": 2550,
          "width": 3509,
          "images": [
            {
              "@id": "https://dlc.services/iiif-img/10/1/skinner_st_DP04117.tif/anno",
              "@type": "oa:Annotation",
              "motivation": "sc:painting",
              "resource": {
                "@id": "https://dlc.services/iiif-img/10/1/skinner_st_DP04117.tif/full/!2000,2000/0/default.jpg",
                "@type": "dctypes:Image",
                "height": 2550,
                "width": 3509,
                "service": {
                  "@id": "https://dlc.services/iiif-img/10/1/skinner_st_DP04117.tif",
                  "protocol": "http://iiif.io/api/image",
                  "height": 2550,
                  "width": 3509,
                  "profile": "http://iiif.io/api/image/2/level1.json"
                }
              },
              "on": "https://digirati-co-uk.github.io/nlw-rcamw/skinner_st.json/sequence/0/canvas/5"
            }
          ]
        },
        {
          "@id": "https://digirati-co-uk.github.io/nlw-rcamw/skinner_st.json/sequence/0/canvas/6",
          "@type": "sc:Canvas",
          "thumbnail": {
            "@id": "https://dlc.services/thumbs/10/1/skinner_st_DP04118.tif/full/full/0/default.jpg",
            "@type": "dctypes:Image",
            "service": {
              "@context": "http://iiif.io/api/image/2/context.json",
              "@id": "https://dlc.services/thumbs/10/1/skinner_st_DP04118.tif",
              "profile": [
                "http://iiif.io/api/image/2/level0.json",
                {
                  "formats": [
                    "jpg"
                  ],
                  "qualities": [
                    "color"
                  ],
                  "supports": [
                    "sizeByWhListed"
                  ]
                }
              ],
              "width": 744,
              "height": 1024,
              "sizes": [
                {
                  "width": 744,
                  "height": 1024
                },
                {
                  "width": 291,
                  "height": 400
                },
                {
                  "width": 145,
                  "height": 200
                },
                {
                  "width": 73,
                  "height": 100
                }
              ]
            }
          },
          "height": 3509,
          "width": 2550,
          "images": [
            {
              "@id": "https://dlc.services/iiif-img/10/1/skinner_st_DP04118.tif/anno",
              "@type": "oa:Annotation",
              "motivation": "sc:painting",
              "resource": {
                "@id": "https://dlc.services/iiif-img/10/1/skinner_st_DP04118.tif/full/!2000,2000/0/default.jpg",
                "@type": "dctypes:Image",
                "height": 3509,
                "width": 2550,
                "service": {
                  "@id": "https://dlc.services/iiif-img/10/1/skinner_st_DP04118.tif",
                  "protocol": "http://iiif.io/api/image",
                  "height": 3509,
                  "width": 2550,
                  "profile": "http://iiif.io/api/image/2/level1.json"
                }
              },
              "on": "https://digirati-co-uk.github.io/nlw-rcamw/skinner_st.json/sequence/0/canvas/6"
            }
          ]
        },
        {
          "@id": "https://digirati-co-uk.github.io/nlw-rcamw/skinner_st.json/sequence/0/canvas/7",
          "@type": "sc:Canvas",
          "thumbnail": {
            "@id": "https://dlc.services/thumbs/10/1/skinner_st_DP04119.tif/full/full/0/default.jpg",
            "@type": "dctypes:Image",
            "service": {
              "@context": "http://iiif.io/api/image/2/context.json",
              "@id": "https://dlc.services/thumbs/10/1/skinner_st_DP04119.tif",
              "profile": [
                "http://iiif.io/api/image/2/level0.json",
                {
                  "formats": [
                    "jpg"
                  ],
                  "qualities": [
                    "color"
                  ],
                  "supports": [
                    "sizeByWhListed"
                  ]
                }
              ],
              "width": 1024,
              "height": 744,
              "sizes": [
                {
                  "width": 1024,
                  "height": 744
                },
                {
                  "width": 400,
                  "height": 291
                },
                {
                  "width": 200,
                  "height": 145
                },
                {
                  "width": 100,
                  "height": 73
                }
              ]
            }
          },
          "height": 2550,
          "width": 3509,
          "images": [
            {
              "@id": "https://dlc.services/iiif-img/10/1/skinner_st_DP04119.tif/anno",
              "@type": "oa:Annotation",
              "motivation": "sc:painting",
              "resource": {
                "@id": "https://dlc.services/iiif-img/10/1/skinner_st_DP04119.tif/full/!2000,2000/0/default.jpg",
                "@type": "dctypes:Image",
                "height": 2550,
                "width": 3509,
                "service": {
                  "@id": "https://dlc.services/iiif-img/10/1/skinner_st_DP04119.tif",
                  "protocol": "http://iiif.io/api/image",
                  "height": 2550,
                  "width": 3509,
                  "profile": "http://iiif.io/api/image/2/level1.json"
                }
              },
              "on": "https://digirati-co-uk.github.io/nlw-rcamw/skinner_st.json/sequence/0/canvas/7"
            }
          ]
        },
        {
          "@id": "https://digirati-co-uk.github.io/nlw-rcamw/skinner_st.json/sequence/0/canvas/8",
          "@type": "sc:Canvas",
          "thumbnail": {
            "@id": "https://dlc.services/thumbs/10/1/skinner_st_DP04120.tif/full/full/0/default.jpg",
            "@type": "dctypes:Image",
            "service": {
              "@context": "http://iiif.io/api/image/2/context.json",
              "@id": "https://dlc.services/thumbs/10/1/skinner_st_DP04120.tif",
              "profile": [
                "http://iiif.io/api/image/2/level0.json",
                {
                  "formats": [
                    "jpg"
                  ],
                  "qualities": [
                    "color"
                  ],
                  "supports": [
                    "sizeByWhListed"
                  ]
                }
              ],
              "width": 1024,
              "height": 744,
              "sizes": [
                {
                  "width": 1024,
                  "height": 744
                },
                {
                  "width": 400,
                  "height": 291
                },
                {
                  "width": 200,
                  "height": 145
                },
                {
                  "width": 100,
                  "height": 73
                }
              ]
            }
          },
          "height": 2550,
          "width": 3509,
          "images": [
            {
              "@id": "https://dlc.services/iiif-img/10/1/skinner_st_DP04120.tif/anno",
              "@type": "oa:Annotation",
              "motivation": "sc:painting",
              "resource": {
                "@id": "https://dlc.services/iiif-img/10/1/skinner_st_DP04120.tif/full/!2000,2000/0/default.jpg",
                "@type": "dctypes:Image",
                "height": 2550,
                "width": 3509,
                "service": {
                  "@id": "https://dlc.services/iiif-img/10/1/skinner_st_DP04120.tif",
                  "protocol": "http://iiif.io/api/image",
                  "height": 2550,
                  "width": 3509,
                  "profile": "http://iiif.io/api/image/2/level1.json"
                }
              },
              "on": "https://digirati-co-uk.github.io/nlw-rcamw/skinner_st.json/sequence/0/canvas/8"
            }
          ]
        },
        {
          "@id": "https://digirati-co-uk.github.io/nlw-rcamw/skinner_st.json/sequence/0/canvas/9",
          "@type": "sc:Canvas",
          "thumbnail": {
            "@id": "https://dlc.services/thumbs/10/1/skinner_st_DP04121.tif/full/full/0/default.jpg",
            "@type": "dctypes:Image",
            "service": {
              "@context": "http://iiif.io/api/image/2/context.json",
              "@id": "https://dlc.services/thumbs/10/1/skinner_st_DP04121.tif",
              "profile": [
                "http://iiif.io/api/image/2/level0.json",
                {
                  "formats": [
                    "jpg"
                  ],
                  "qualities": [
                    "color"
                  ],
                  "supports": [
                    "sizeByWhListed"
                  ]
                }
              ],
              "width": 744,
              "height": 1024,
              "sizes": [
                {
                  "width": 744,
                  "height": 1024
                },
                {
                  "width": 291,
                  "height": 400
                },
                {
                  "width": 145,
                  "height": 200
                },
                {
                  "width": 73,
                  "height": 100
                }
              ]
            }
          },
          "height": 3509,
          "width": 2550,
          "images": [
            {
              "@id": "https://dlc.services/iiif-img/10/1/skinner_st_DP04121.tif/anno",
              "@type": "oa:Annotation",
              "motivation": "sc:painting",
              "resource": {
                "@id": "https://dlc.services/iiif-img/10/1/skinner_st_DP04121.tif/full/!2000,2000/0/default.jpg",
                "@type": "dctypes:Image",
                "height": 3509,
                "width": 2550,
                "service": {
                  "@id": "https://dlc.services/iiif-img/10/1/skinner_st_DP04121.tif",
                  "protocol": "http://iiif.io/api/image",
                  "height": 3509,
                  "width": 2550,
                  "profile": "http://iiif.io/api/image/2/level1.json"
                }
              },
              "on": "https://digirati-co-uk.github.io/nlw-rcamw/skinner_st.json/sequence/0/canvas/9"
            }
          ]
        },
        {
          "@id": "https://digirati-co-uk.github.io/nlw-rcamw/skinner_st.json/sequence/0/canvas/10",
          "@type": "sc:Canvas",
          "thumbnail": {
            "@id": "https://dlc.services/thumbs/10/1/skinner_st_DP04122.tif/full/full/0/default.jpg",
            "@type": "dctypes:Image",
            "service": {
              "@context": "http://iiif.io/api/image/2/context.json",
              "@id": "https://dlc.services/thumbs/10/1/skinner_st_DP04122.tif",
              "profile": [
                "http://iiif.io/api/image/2/level0.json",
                {
                  "formats": [
                    "jpg"
                  ],
                  "qualities": [
                    "color"
                  ],
                  "supports": [
                    "sizeByWhListed"
                  ]
                }
              ],
              "width": 744,
              "height": 1024,
              "sizes": [
                {
                  "width": 744,
                  "height": 1024
                },
                {
                  "width": 291,
                  "height": 400
                },
                {
                  "width": 145,
                  "height": 200
                },
                {
                  "width": 73,
                  "height": 100
                }
              ]
            }
          },
          "height": 3509,
          "width": 2550,
          "images": [
            {
              "@id": "https://dlc.services/iiif-img/10/1/skinner_st_DP04122.tif/anno",
              "@type": "oa:Annotation",
              "motivation": "sc:painting",
              "resource": {
                "@id": "https://dlc.services/iiif-img/10/1/skinner_st_DP04122.tif/full/!2000,2000/0/default.jpg",
                "@type": "dctypes:Image",
                "height": 3509,
                "width": 2550,
                "service": {
                  "@id": "https://dlc.services/iiif-img/10/1/skinner_st_DP04122.tif",
                  "protocol": "http://iiif.io/api/image",
                  "height": 3509,
                  "width": 2550,
                  "profile": "http://iiif.io/api/image/2/level1.json"
                }
              },
              "on": "https://digirati-co-uk.github.io/nlw-rcamw/skinner_st.json/sequence/0/canvas/10"
            }
          ]
        },
        {
          "@id": "https://digirati-co-uk.github.io/nlw-rcamw/skinner_st.json/sequence/0/canvas/11",
          "@type": "sc:Canvas",
          "thumbnail": {
            "@id": "https://dlc.services/thumbs/10/1/skinner_st_DP04123.tif/full/full/0/default.jpg",
            "@type": "dctypes:Image",
            "service": {
              "@context": "http://iiif.io/api/image/2/context.json",
              "@id": "https://dlc.services/thumbs/10/1/skinner_st_DP04123.tif",
              "profile": [
                "http://iiif.io/api/image/2/level0.json",
                {
                  "formats": [
                    "jpg"
                  ],
                  "qualities": [
                    "color"
                  ],
                  "supports": [
                    "sizeByWhListed"
                  ]
                }
              ],
              "width": 1024,
              "height": 744,
              "sizes": [
                {
                  "width": 1024,
                  "height": 744
                },
                {
                  "width": 400,
                  "height": 291
                },
                {
                  "width": 200,
                  "height": 145
                },
                {
                  "width": 100,
                  "height": 73
                }
              ]
            }
          },
          "height": 2550,
          "width": 3509,
          "images": [
            {
              "@id": "https://dlc.services/iiif-img/10/1/skinner_st_DP04123.tif/anno",
              "@type": "oa:Annotation",
              "motivation": "sc:painting",
              "resource": {
                "@id": "https://dlc.services/iiif-img/10/1/skinner_st_DP04123.tif/full/!2000,2000/0/default.jpg",
                "@type": "dctypes:Image",
                "height": 2550,
                "width": 3509,
                "service": {
                  "@id": "https://dlc.services/iiif-img/10/1/skinner_st_DP04123.tif",
                  "protocol": "http://iiif.io/api/image",
                  "height": 2550,
                  "width": 3509,
                  "profile": "http://iiif.io/api/image/2/level1.json"
                }
              },
              "on": "https://digirati-co-uk.github.io/nlw-rcamw/skinner_st.json/sequence/0/canvas/11"
            }
          ]
        },
        {
          "@id": "https://digirati-co-uk.github.io/nlw-rcamw/skinner_st.json/sequence/0/canvas/12",
          "@type": "sc:Canvas",
          "thumbnail": {
            "@id": "https://dlc.services/thumbs/10/1/skinner_st_DP04124.tif/full/full/0/default.jpg",
            "@type": "dctypes:Image",
            "service": {
              "@context": "http://iiif.io/api/image/2/context.json",
              "@id": "https://dlc.services/thumbs/10/1/skinner_st_DP04124.tif",
              "profile": [
                "http://iiif.io/api/image/2/level0.json",
                {
                  "formats": [
                    "jpg"
                  ],
                  "qualities": [
                    "color"
                  ],
                  "supports": [
                    "sizeByWhListed"
                  ]
                }
              ],
              "width": 1024,
              "height": 744,
              "sizes": [
                {
                  "width": 1024,
                  "height": 744
                },
                {
                  "width": 400,
                  "height": 291
                },
                {
                  "width": 200,
                  "height": 145
                },
                {
                  "width": 100,
                  "height": 73
                }
              ]
            }
          },
          "height": 2550,
          "width": 3509,
          "images": [
            {
              "@id": "https://dlc.services/iiif-img/10/1/skinner_st_DP04124.tif/anno",
              "@type": "oa:Annotation",
              "motivation": "sc:painting",
              "resource": {
                "@id": "https://dlc.services/iiif-img/10/1/skinner_st_DP04124.tif/full/!2000,2000/0/default.jpg",
                "@type": "dctypes:Image",
                "height": 2550,
                "width": 3509,
                "service": {
                  "@id": "https://dlc.services/iiif-img/10/1/skinner_st_DP04124.tif",
                  "protocol": "http://iiif.io/api/image",
                  "height": 2550,
                  "width": 3509,
                  "profile": "http://iiif.io/api/image/2/level1.json"
                }
              },
              "on": "https://digirati-co-uk.github.io/nlw-rcamw/skinner_st.json/sequence/0/canvas/12"
            }
          ]
        },
        {
          "@id": "https://digirati-co-uk.github.io/nlw-rcamw/skinner_st.json/sequence/0/canvas/13",
          "@type": "sc:Canvas",
          "thumbnail": {
            "@id": "https://dlc.services/thumbs/10/1/skinner_st_DP04125.tif/full/full/0/default.jpg",
            "@type": "dctypes:Image",
            "service": {
              "@context": "http://iiif.io/api/image/2/context.json",
              "@id": "https://dlc.services/thumbs/10/1/skinner_st_DP04125.tif",
              "profile": [
                "http://iiif.io/api/image/2/level0.json",
                {
                  "formats": [
                    "jpg"
                  ],
                  "qualities": [
                    "color"
                  ],
                  "supports": [
                    "sizeByWhListed"
                  ]
                }
              ],
              "width": 1024,
              "height": 744,
              "sizes": [
                {
                  "width": 1024,
                  "height": 744
                },
                {
                  "width": 400,
                  "height": 291
                },
                {
                  "width": 200,
                  "height": 145
                },
                {
                  "width": 100,
                  "height": 73
                }
              ]
            }
          },
          "height": 2550,
          "width": 3509,
          "images": [
            {
              "@id": "https://dlc.services/iiif-img/10/1/skinner_st_DP04125.tif/anno",
              "@type": "oa:Annotation",
              "motivation": "sc:painting",
              "resource": {
                "@id": "https://dlc.services/iiif-img/10/1/skinner_st_DP04125.tif/full/!2000,2000/0/default.jpg",
                "@type": "dctypes:Image",
                "height": 2550,
                "width": 3509,
                "service": {
                  "@id": "https://dlc.services/iiif-img/10/1/skinner_st_DP04125.tif",
                  "protocol": "http://iiif.io/api/image",
                  "height": 2550,
                  "width": 3509,
                  "profile": "http://iiif.io/api/image/2/level1.json"
                }
              },
              "on": "https://digirati-co-uk.github.io/nlw-rcamw/skinner_st.json/sequence/0/canvas/13"
            }
          ]
        },
        {
          "@id": "https://digirati-co-uk.github.io/nlw-rcamw/skinner_st.json/sequence/0/canvas/14",
          "@type": "sc:Canvas",
          "thumbnail": {
            "@id": "https://dlc.services/thumbs/10/1/skinner_st_DP04126.tif/full/full/0/default.jpg",
            "@type": "dctypes:Image",
            "service": {
              "@context": "http://iiif.io/api/image/2/context.json",
              "@id": "https://dlc.services/thumbs/10/1/skinner_st_DP04126.tif",
              "profile": [
                "http://iiif.io/api/image/2/level0.json",
                {
                  "formats": [
                    "jpg"
                  ],
                  "qualities": [
                    "color"
                  ],
                  "supports": [
                    "sizeByWhListed"
                  ]
                }
              ],
              "width": 744,
              "height": 1024,
              "sizes": [
                {
                  "width": 744,
                  "height": 1024
                },
                {
                  "width": 291,
                  "height": 400
                },
                {
                  "width": 145,
                  "height": 200
                },
                {
                  "width": 73,
                  "height": 100
                }
              ]
            }
          },
          "height": 3509,
          "width": 2550,
          "images": [
            {
              "@id": "https://dlc.services/iiif-img/10/1/skinner_st_DP04126.tif/anno",
              "@type": "oa:Annotation",
              "motivation": "sc:painting",
              "resource": {
                "@id": "https://dlc.services/iiif-img/10/1/skinner_st_DP04126.tif/full/!2000,2000/0/default.jpg",
                "@type": "dctypes:Image",
                "height": 3509,
                "width": 2550,
                "service": {
                  "@id": "https://dlc.services/iiif-img/10/1/skinner_st_DP04126.tif",
                  "protocol": "http://iiif.io/api/image",
                  "height": 3509,
                  "width": 2550,
                  "profile": "http://iiif.io/api/image/2/level1.json"
                }
              },
              "on": "https://digirati-co-uk.github.io/nlw-rcamw/skinner_st.json/sequence/0/canvas/14"
            }
          ]
        },
        {
          "@id": "https://digirati-co-uk.github.io/nlw-rcamw/skinner_st.json/sequence/0/canvas/15",
          "@type": "sc:Canvas",
          "thumbnail": {
            "@id": "https://dlc.services/thumbs/10/1/skinner_st_DP04127.tif/full/full/0/default.jpg",
            "@type": "dctypes:Image",
            "service": {
              "@context": "http://iiif.io/api/image/2/context.json",
              "@id": "https://dlc.services/thumbs/10/1/skinner_st_DP04127.tif",
              "profile": [
                "http://iiif.io/api/image/2/level0.json",
                {
                  "formats": [
                    "jpg"
                  ],
                  "qualities": [
                    "color"
                  ],
                  "supports": [
                    "sizeByWhListed"
                  ]
                }
              ],
              "width": 1024,
              "height": 744,
              "sizes": [
                {
                  "width": 1024,
                  "height": 744
                },
                {
                  "width": 400,
                  "height": 291
                },
                {
                  "width": 200,
                  "height": 145
                },
                {
                  "width": 100,
                  "height": 73
                }
              ]
            }
          },
          "height": 2550,
          "width": 3509,
          "images": [
            {
              "@id": "https://dlc.services/iiif-img/10/1/skinner_st_DP04127.tif/anno",
              "@type": "oa:Annotation",
              "motivation": "sc:painting",
              "resource": {
                "@id": "https://dlc.services/iiif-img/10/1/skinner_st_DP04127.tif/full/!2000,2000/0/default.jpg",
                "@type": "dctypes:Image",
                "height": 2550,
                "width": 3509,
                "service": {
                  "@id": "https://dlc.services/iiif-img/10/1/skinner_st_DP04127.tif",
                  "protocol": "http://iiif.io/api/image",
                  "height": 2550,
                  "width": 3509,
                  "profile": "http://iiif.io/api/image/2/level1.json"
                }
              },
              "on": "https://digirati-co-uk.github.io/nlw-rcamw/skinner_st.json/sequence/0/canvas/15"
            }
          ]
        }
      ]
    }
  ]
}